test_pycasbin/__init__.py
test_pycasbin-0.1.0.dist-info/METADATA
test_pycasbin-0.1.0.dist-info/WHEEL
test_pycasbin-0.1.0.dist-info/top_level.txt
test_pycasbin-0.1.0.dist-info/RECORD
