Metadata-Version: 2.1
Name: test-pycasbin
Version: 0.1.0
Summary: test-pycasbin
Home-page: https://github.com/yyellowsun/test-pycasbin
Author: yyellowsun
Author-email: coder328@163.com
License: UNKNOWN
Platform: UNKNOWN
